rinoh_typeface_texgyrepagella/GUST-FONT-LICENSE.txt
rinoh_typeface_texgyrepagella/README-TeX-Gyre-Pagella.txt
rinoh_typeface_texgyrepagella/__init__.py
rinoh_typeface_texgyrepagella/texgyrepagella-bold.otf
rinoh_typeface_texgyrepagella/texgyrepagella-bolditalic.otf
rinoh_typeface_texgyrepagella/texgyrepagella-italic.otf
rinoh_typeface_texgyrepagella/texgyrepagella-regular.otf
rinoh_typeface_texgyrepagella-0.1.1.dist-info/DESCRIPTION.rst
rinoh_typeface_texgyrepagella-0.1.1.dist-info/METADATA
rinoh_typeface_texgyrepagella-0.1.1.dist-info/RECORD
rinoh_typeface_texgyrepagella-0.1.1.dist-info/WHEEL
rinoh_typeface_texgyrepagella-0.1.1.dist-info/entry_points.txt
rinoh_typeface_texgyrepagella-0.1.1.dist-info/metadata.json
rinoh_typeface_texgyrepagella-0.1.1.dist-info/top_level.txt
